LICENSE
MANIFEST.in
README.rst
setup.py
ludolph_doorman/__init__.py
ludolph_doorman/serve.py
ludolph_doorman.egg-info/PKG-INFO
ludolph_doorman.egg-info/SOURCES.txt
ludolph_doorman.egg-info/dependency_links.txt
ludolph_doorman.egg-info/requires.txt
ludolph_doorman.egg-info/top_level.txt