Metadata-Version: 1.1
Name: ludolph-doorman
Version: 1.2
Summary: Ludolph: Doorman plugin
Home-page: https://github.com/ricco386/ludolph-doorman/
Author: Richard Kellner
Author-email: richard.kellner [at] gmail.com
License: MIT
Platform: any
Classifier: Environment :: Console
Classifier: Environment :: Plugins
Classifier: Intended Audience :: Developers
Classifier: Intended Audience :: Education
Classifier: Intended Audience :: System Administrators
Classifier: License :: OSI Approved :: MIT License
Classifier: Operating System :: MacOS
Classifier: Operating System :: POSIX
Classifier: Operating System :: Unix
Classifier: Programming Language :: Python
Classifier: Programming Language :: Python :: 2
Classifier: Programming Language :: Python :: 3
Classifier: Topic :: Communications :: Chat
Classifier: Topic :: Utilities
